zoracloud/__init__.py
zoracloud/crud_backend/__init__.py
zoracloud/crud_backend/authn.py
zoracloud/crud_backend/authz.py
zoracloud/crud_backend/config.py
zoracloud/crud_backend/csrf.py
zoracloud/crud_backend/decorators.py
zoracloud/crud_backend/helpers.py
zoracloud/crud_backend/probes.py
zoracloud/crud_backend/serving.py
zoracloud/crud_backend/settings.py
zoracloud/crud_backend/status.py
zoracloud/crud_backend/api/__init__.py
zoracloud/crud_backend/api/apis.py
zoracloud/crud_backend/api/custom_resource.py
zoracloud/crud_backend/api/namespace.py
zoracloud/crud_backend/api/node.py
zoracloud/crud_backend/api/notebook.py
zoracloud/crud_backend/api/pod.py
zoracloud/crud_backend/api/poddefault.py
zoracloud/crud_backend/api/pvc.py
zoracloud/crud_backend/api/secret.py
zoracloud/crud_backend/api/storageclass.py
zoracloud/crud_backend/api/utils.py
zoracloud/crud_backend/errors/__init__.py
zoracloud/crud_backend/errors/handlers.py
zoracloud/crud_backend/errors/utils.py
zoracloud/crud_backend/rok/__init__.py
zoracloud/crud_backend/rok/routes.py
zoracloud/crud_backend/routes/__init__.py
zoracloud/crud_backend/routes/get.py
zoracloud-0.0.0.dist-info/METADATA
zoracloud-0.0.0.dist-info/WHEEL
zoracloud-0.0.0.dist-info/top_level.txt
zoracloud-0.0.0.dist-info/RECORD
