Metadata-Version: 2.1
Name: zoracloud
Version: 0.0.0
Summary: A package with a base Flask CRUD backend common code
Home-page: UNKNOWN
Author: allankiplangat22@gmail.com
License: UNKNOWN
Platform: UNKNOWN
Classifier: Programming Language :: Python :: 3
Classifier: License :: OSI Approved :: Apache Software License
Classifier: Topic :: Software Development
Classifier: Topic :: Software Development :: Libraries
Classifier: Topic :: Software Development :: Libraries :: Python Modules
Requires-Python: >=3.6
Requires-Dist: Flask (>=1.1.1)
Requires-Dist: Flask-API (>=2.0)
Requires-Dist: kubernetes (<11.0.0,>=10.0.1)
Requires-Dist: requests (>=2.22.0)
Requires-Dist: urllib3 (>=1.25.7)
Requires-Dist: Werkzeug (>=0.16.0)
Requires-Dist: Flask-Cors (>=3.0.8)
